Metadata-Version: 2.1
Name: sum-04117
Version: 0.0.1
Summary: adding number
Home-page: https://github.com/Pushkar-Singh-14/
Author: Hamza Bhatti
Author-email: hbhati006@gmail.com
License: UNKNOWN
Platform: UNKNOWN
Classifier: Programming Language :: Python :: 3
Classifier: License :: OSI Approved :: MIT License
Classifier: Operating System :: OS Independent
